unitycatalog/ai/langchain/__init__.py
unitycatalog/ai/langchain/toolkit.py
unitycatalog/ai/langchain/version.py
unitycatalog_langchain-0.3.0.dist-info/METADATA
unitycatalog_langchain-0.3.0.dist-info/WHEEL
unitycatalog_langchain-0.3.0.dist-info/RECORD
