Metadata-Version: 2.4
Name: unitycatalog-langchain
Version: 0.3.0
Summary: Support for Unity Catalog functions as LangChain tools
Author-email: Serena Ruan <serena.ruan@databricks.com>
License: Apache-2.0
Requires-Python: >=3.10
Requires-Dist: langchain-community>=0.4.0
Requires-Dist: langchain>=1.0.0
Requires-Dist: unitycatalog-ai
Provides-Extra: databricks
Requires-Dist: unitycatalog-ai[databricks]; extra == 'databricks'
Provides-Extra: databricks-dev
Requires-Dist: databricks-langchain; extra == 'databricks-dev'
Requires-Dist: langgraph; extra == 'databricks-dev'
Requires-Dist: unitycatalog-ai[databricks-dev]; extra == 'databricks-dev'
Provides-Extra: dev
Requires-Dist: databricks-langchain; extra == 'dev'
Requires-Dist: langgraph; extra == 'dev'
Requires-Dist: unitycatalog-ai[dev]; extra == 'dev'
